random_plugin.py
setup.py
pytest_random.egg-info/PKG-INFO
pytest_random.egg-info/SOURCES.txt
pytest_random.egg-info/dependency_links.txt
pytest_random.egg-info/entry_points.txt
pytest_random.egg-info/requires.txt
pytest_random.egg-info/top_level.txt