Metadata-Version: 1.0
Name: pytest-random
Version: 0.01
Summary: py.test plugin to randomize tests
Home-page: https://github.com/klrmn/pytest-random
Author: Leah Klearman
Author-email: lklrmn@gmail.com
License: Mozilla Public License 2.0 (MPL 2.0)
Keywords: py.test pytest qa
Platform: UNKNOWN
Classifier: Development Status :: 2 - Pre-Alpha
Classifier: Intended Audience :: Developers
Classifier: License :: OSI Approved :: Mozilla Public License 2.0 (MPL 2.0)
Classifier: Operating System :: POSIX
Classifier: Operating System :: Microsoft :: Windows
Classifier: Operating System :: MacOS :: MacOS X
Classifier: Topic :: Software Development :: Quality Assurance
Classifier: Topic :: Software Development :: Testing
Classifier: Topic :: Utilities
Classifier: Programming Language :: Python
Classifier: Programming Language :: Python :: 2.6
Classifier: Programming Language :: Python :: 2.7
